__init__.py
hello.py
mechalodon-0.0.0.dist-info/METADATA
mechalodon-0.0.0.dist-info/WHEEL
mechalodon-0.0.0.dist-info/top_level.txt
mechalodon-0.0.0.dist-info/RECORD
